binance_async_client/__init__.py
binance_async_client/client.py
binance_async_client/futures_client.py
binance_async_client/rate_limiter.py
binance_async_client-0.1.0.dist-info/licenses/LICENSE
binance_async_client-0.1.0.dist-info/METADATA
binance_async_client-0.1.0.dist-info/WHEEL
binance_async_client-0.1.0.dist-info/top_level.txt
binance_async_client-0.1.0.dist-info/RECORD
