Metadata-Version: 2.4
Name: binance-async-client
Version: 0.1.0
Summary: 异步币安API客户端，支持现货和期货交易，内置智能限流器
Author: binance-async-client contributors
License: MIT
Project-URL: Homepage, https://github.com/hamartia0/binance-async-client
Project-URL: Documentation, https://github.com/hamartia0/binance-async-client#readme
Project-URL: Repository, https://github.com/hamartia0/binance-async-client
Project-URL: Issues, https://github.com/hamartia0/binance-async-client/issues
Keywords: binance,async,api,client,cryptocurrency,trading
Classifier: Development Status :: 4 - Beta
Classifier: Intended Audience :: Developers
Classifier: License :: OSI Approved :: MIT License
Classifier: Programming Language :: Python :: 3
Classifier: Programming Language :: Python :: 3.8
Classifier: Programming Language :: Python :: 3.9
Classifier: Programming Language :: Python :: 3.10
Classifier: Programming Language :: Python :: 3.11
Classifier: Programming Language :: Python :: 3.12
Classifier: Topic :: Software Development :: Libraries :: Python Modules
Classifier: Topic :: Office/Business :: Financial :: Investment
Requires-Python: >=3.8
License-File: LICENSE
Requires-Dist: aiohttp>=3.8.0
Provides-Extra: dev
Requires-Dist: pytest>=7.0.0; extra == "dev"
Requires-Dist: pytest-asyncio>=0.21.0; extra == "dev"
Dynamic: license-file
